ctu_mitsubishi/__init__.py
ctu_mitsubishi/basler_camera.py
ctu_mitsubishi/rv6s.py
ctu_mitsubishi/rv6s_gripper.py
ctu_mitsubishi/utils.py
ctu_mitsubishi-0.1.5.dist-info/licenses/LICENSE
ctu_mitsubishi-0.1.5.dist-info/METADATA
ctu_mitsubishi-0.1.5.dist-info/WHEEL
ctu_mitsubishi-0.1.5.dist-info/top_level.txt
ctu_mitsubishi-0.1.5.dist-info/RECORD
