Metadata-Version: 2.4
Name: ctu_mitsubishi
Version: 0.1.5
Summary: Package to control CTU/CIIRC robots Mitsubishi.
Author-email: Vladimir Petrik <vladimir.petrik@cvut.cz>
License: BSD 3-Clause
Requires-Python: >=3.10
License-File: LICENSE
Requires-Dist: pyserial>=3.5
Requires-Dist: numpy>=2.1.3
Requires-Dist: pypylon>=4.2.0
Provides-Extra: dev
Requires-Dist: black>=25.9.0; extra == "dev"
Requires-Dist: pre-commit>=4.3.0; extra == "dev"
Requires-Dist: pytest>=8.4.2; extra == "dev"
Requires-Dist: ruff>=0.13.2; extra == "dev"
Dynamic: license-file
